fastapi_mongo_admin/__init__.py
fastapi_mongo_admin/auth.py
fastapi_mongo_admin/cache.py
fastapi_mongo_admin/database.py
fastapi_mongo_admin/exceptions.py
fastapi_mongo_admin/middleware.py
fastapi_mongo_admin/models.py
fastapi_mongo_admin/pagination.py
fastapi_mongo_admin/router.py
fastapi_mongo_admin/schema.py
fastapi_mongo_admin/services.py
fastapi_mongo_admin/utils.py
fastapi_mongo_admin/static/admin.html
fastapi_mongo_admin/static/css/darkmode.css
fastapi_mongo_admin/static/css/lightmode.css
fastapi_mongo_admin/static/css/tailwind.css
fastapi_mongo_admin/static/js/api.js
fastapi_mongo_admin/static/js/babel.min.js
fastapi_mongo_admin/static/js/chart.umd.min.js
fastapi_mongo_admin/static/js/darkmode.js
fastapi_mongo_admin/static/js/export-progress.js
fastapi_mongo_admin/static/js/keyboard.js
fastapi_mongo_admin/static/js/query-builder.js
fastapi_mongo_admin/static/js/react-dom.production.min.js
fastapi_mongo_admin/static/js/react.production.min.js
fastapi_mongo_admin/static/js/table.js
fastapi_mongo_admin/static/js/toast.js
fastapi_mongo_admin/static/js/utils.js
fastapi_mongo_admin/static/js/react/App.js
fastapi_mongo_admin/static/js/react/jsx-helpers.js
fastapi_mongo_admin/static/js/react/utils.js
fastapi_mongo_admin/static/js/react/components/AnalyticsView.js
fastapi_mongo_admin/static/js/react/components/BrowseView.js
fastapi_mongo_admin/static/js/react/components/BulkUpdateModal.js
fastapi_mongo_admin/static/js/react/components/ConfirmModal.js
fastapi_mongo_admin/static/js/react/components/CreateModal.js
fastapi_mongo_admin/static/js/react/components/CustomActionsModal.js
fastapi_mongo_admin/static/js/react/components/CustomView.js
fastapi_mongo_admin/static/js/react/components/DateHierarchy.js
fastapi_mongo_admin/static/js/react/components/EditModal.js
fastapi_mongo_admin/static/js/react/components/ExportModal.js
fastapi_mongo_admin/static/js/react/components/FieldSelectionModal.js
fastapi_mongo_admin/static/js/react/components/FilterPanel.js
fastapi_mongo_admin-0.1.2.dist-info/licenses/LICENSE
fastapi_mongo_admin-0.1.2.dist-info/METADATA
fastapi_mongo_admin-0.1.2.dist-info/WHEEL
fastapi_mongo_admin-0.1.2.dist-info/top_level.txt
fastapi_mongo_admin-0.1.2.dist-info/RECORD
