Metadata-Version: 2.4
Name: fastapi-mongo-admin
Version: 0.1.2
Summary: A FastAPI package for MongoDB admin operations with generic CRUD endpoints and admin UI
Author-email: Taiwo Kareem <taiwo.kareem36@gmail.com>
License: MIT
Project-URL: Homepage, https://github.com/tushortz/fastapi-mongo-admin
Project-URL: Documentation, https://github.com/tushortz/fastapi-mongo-admin#readme
Project-URL: Repository, https://github.com/tushortz/fastapi-mongo-admin
Project-URL: Issues, https://github.com/tushortz/fastapi-mongo-admin/issues
Keywords: fastapi,mongodb,admin,crud,motor,rest-api
Classifier: Development Status :: 4 - Beta
Classifier: Intended Audience :: Developers
Classifier: License :: OSI Approved :: MIT License
Classifier: Programming Language :: Python :: 3
Classifier: Programming Language :: Python :: 3.9
Classifier: Programming Language :: Python :: 3.10
Classifier: Programming Language :: Python :: 3.11
Classifier: Programming Language :: Python :: 3.12
Classifier: Framework :: FastAPI
Classifier: Topic :: Database
Classifier: Topic :: Internet :: WWW/HTTP :: HTTP Servers
Requires-Python: >=3.9
License-File: LICENSE
Requires-Dist: fastapi>=0.68.0
Requires-Dist: motor>=2.5.0
Requires-Dist: pymongo>=4.0.0
Requires-Dist: pydantic<3.0.0,>=2.0.0
Provides-Extra: dev
Requires-Dist: pytest>=8.3.0; extra == "dev"
Requires-Dist: pytest-asyncio>=0.24.0; extra == "dev"
Requires-Dist: black>=24.8.0; extra == "dev"
Requires-Dist: ruff>=0.6.0; extra == "dev"
Provides-Extra: export
Requires-Dist: pyyaml>=6.0; extra == "export"
Requires-Dist: tomli>=2.0.0; python_version < "3.11" and extra == "export"
Requires-Dist: tomli-w>=1.0.0; extra == "export"
Dynamic: license-file
